{
  "from": [
    { "id": "f1", "label": "Asthma" },
    { "id": "f2", "label": "Diabetes" },
    { "id": "f3", "label": "High blood pressure" },
    { "id": "f4", "label": "Over 40 years old" },
    { "id": "f5", "label": "Excessive alcohol consumption" },
    { "id": "f6", "label": "Smoker" },
    { "id": "f7", "label": "Frequent attender" },
    { "id": "f8", "label": "Stroke" },
    { "id": "f9", "label": "Frail" },
    { "id": "f10", "label": "Epilepsy" },
    { "id": "f11", "label": "Depression" },
    { "id": "f12", "label": "COPD" }
  ],
  "to": [
    [
      { "id": "t1", "label": "Constituent 1", "fill": "#0543bc" },
      { "id": "t2", "label": "Constituent 2", "fill": "#0543bc" },
      { "id": "t3", "label": "Constituent 3", "fill": "#0543bc" },
      { "id": "t4", "label": "Constituent 4", "fill": "#0543bc" },
      { "id": "t5", "label": "Constituent 5", "fill": "#0543bc" },
      { "id": "t6", "label": "Constituent 6", "fill": "#0543bc" },
      { "id": "t7", "label": "Constituent 7", "fill": "#0543bc" },
      { "id": "t8", "label": "Constituent 8", "fill": "#0543bc" },
      { "id": "t9", "label": "Constituent 9", "fill": "#0543bc" },
      { "id": "t10", "label": "Constituent 10", "fill": "#0543bc" },
      { "id": "t11", "label": "Constituent 11", "fill": "#0543bc" },
      { "id": "t12", "label": "Constituent 12", "fill": "#0543bc" },
      { "id": "t13", "label": "Constituent 13", "fill": "#0543bc" },
      { "id": "t14", "label": "Constituent 14", "fill": "#0543bc" },
      { "id": "t15", "label": "Constituent 15", "fill": "#0543bc" },
      { "id": "t16", "label": "Constituent 16", "fill": "#0543bc" },
      { "id": "t17", "label": "Constituent 17", "fill": "#0543bc" },
      { "id": "t18", "label": "Constituent 18", "fill": "#0543bc" },
      { "id": "t19", "label": "Constituent 19", "fill": "#0543bc" },
      { "id": "t20", "label": "Constituent 20", "fill": "#0543bc" },
      { "id": "t21", "label": "Constituent 21", "fill": "#0543bc" },
      { "id": "t22", "label": "Constituent 22", "fill": "#0543bc" },
      { "id": "t23", "label": "Constituent 23", "fill": "#0543bc" },
      { "id": "t24", "label": "Constituent 24", "fill": "#0543bc" },
      { "id": "t25", "label": "Constituent 25", "fill": "#0543bc" },
      { "id": "t26", "label": "Constituent 26", "fill": "#0543bc" },
      { "id": "t27", "label": "Constituent 1", "fill": "#0543bc" },
      { "id": "t28", "label": "Constituent 1", "fill": "#0543bc" },
      { "id": "t29", "label": "Constituent 1", "fill": "#0543bc" },
      { "id": "t30", "label": "Constituent 1", "fill": "#0543bc" },
      { "id": "t31", "label": "Constituent 1", "fill": "#0543bc" },
      { "id": "t32", "label": "Constituent 1", "fill": "#0543bc" },
      { "id": "t33", "label": "Constituent 1", "fill": "#0543bc" },
      { "id": "t34", "label": "Constituent 1", "fill": "#0543bc" },
      { "id": "t35", "label": "Constituent 1", "fill": "#0543bc" },
      { "id": "t36", "label": "Constituent 1", "fill": "#0543bc" },
      { "id": "t37", "label": "Constituent 1", "fill": "#0543bc" },
      { "id": "t38", "label": "Constituent 1", "fill": "#0543bc" },
      { "id": "t39", "label": "Constituent 1", "fill": "#0543bc" },
      { "id": "t40", "label": "Constituent 1", "fill": "#0543bc" },
      { "id": "t41", "label": "Constituent 1", "fill": "#0543bc" },
      { "id": "t42", "label": "Constituent 1", "fill": "#0543bc" },
      { "id": "t43", "label": "Constituent 1", "fill": "#0543bc" },
      { "id": "t44", "label": "Constituent 1", "fill": "#0543bc" },
      { "id": "t45", "label": "Constituent 1", "fill": "#0543bc" },
      { "id": "t46", "label": "Constituent 1", "fill": "#0543bc" },
      { "id": "t47", "label": "Constituent 1", "fill": "#0543bc" },
      { "id": "t48", "label": "Constituent 1", "fill": "#0543bc" },
      { "id": "t49", "label": "Constituent 1", "fill": "#0543bc" },
      { "id": "t50", "label": "Constituent 1", "fill": "#0543bc" },
      { "id": "t51", "label": "Constituent 1", "fill": "#0543bc" },
      { "id": "t52", "label": "Constituent 1", "fill": "#0543bc" },
      { "id": "t53", "label": "Constituent 1", "fill": "#0543bc" },
      { "id": "t54", "label": "Constituent 1", "fill": "#0543bc" },
      { "id": "t55", "label": "Constituent 1", "fill": "#0543bc" },
      { "id": "t56", "label": "Constituent 1", "fill": "#0543bc" },
      { "id": "t57", "label": "Constituent 1", "fill": "#0543bc" },
      { "id": "t58", "label": "Constituent 1", "fill": "#0543bc" },
      { "id": "t59", "label": "Constituent 1", "fill": "#0543bc" },
      { "id": "t60", "label": "Constituent 1", "fill": "#0543bc" },
      { "id": "t61", "label": "Constituent 1", "fill": "#0543bc" },
      { "id": "t62", "label": "Constituent 1", "fill": "#0543bc" },
      { "id": "t63", "label": "Constituent 1", "fill": "#0543bc" },
      { "id": "t64", "label": "Constituent 1", "fill": "#0543bc" },
      { "id": "t65", "label": "Constituent 1", "fill": "#0543bc" },
      { "id": "t66", "label": "Constituent 1", "fill": "#0543bc" },
      { "id": "t67", "label": "Constituent 1", "fill": "#F80018" },
      { "id": "t68", "label": "Constituent 1", "fill": "#0543bc" },
      { "id": "t69", "label": "Constituent 1", "fill": "#0543bc" },
      { "id": "t70", "label": "Constituent 1", "fill": "#0543bc" },
      { "id": "t71", "label": "Constituent 1", "fill": "#0543bc" },
      { "id": "t72", "label": "Constituent 1", "fill": "#0543bc" },
      { "id": "t73", "label": "Constituent 1", "fill": "#0543bc" },
      { "id": "t74", "label": "Constituent 1", "fill": "#0543bc" },
      { "id": "t75", "label": "Constituent 1", "fill": "#0543bc" },
      { "id": "t76", "label": "Constituent 1", "fill": "#0543bc" },
      { "id": "t77", "label": "Constituent 1", "fill": "#0543bc" },
      { "id": "t78", "label": "Constituent 1", "fill": "#0543bc" },
      { "id": "t79", "label": "Constituent 1", "fill": "#0543bc" },
      { "id": "t80", "label": "Constituent 1", "fill": "#0543bc" },
      { "id": "t81", "label": "Constituent 1", "fill": "#0543bc" },
      { "id": "t82", "label": "Constituent 1", "fill": "#0543bc" },
      { "id": "t83", "label": "Constituent 1", "fill": "#0543bc" },
      { "id": "t84", "label": "Constituent 1", "fill": "#0543bc" },
      { "id": "t85", "label": "Constituent 1", "fill": "#0543bc" },
      { "id": "t86", "label": "Constituent 1", "fill": "#0543bc" },
      { "id": "t87", "label": "Constituent 1", "fill": "#0543bc" },
      { "id": "t88", "label": "Constituent 1", "fill": "#0543bc" },
      { "id": "t89", "label": "Constituent 1", "fill": "#0543bc" },
      { "id": "t90", "label": "Constituent 1", "fill": "#0543bc" },
      { "id": "t91", "label": "Constituent 1", "fill": "#0543bc" },
      { "id": "t92", "label": "Constituent 1", "fill": "#0543bc" },
      { "id": "t93", "label": "Constituent 1", "fill": "#0543bc" },
      { "id": "t94", "label": "Constituent 1", "fill": "#0543bc" },
      { "id": "t95", "label": "Constituent 1", "fill": "#0543bc" },
      { "id": "t96", "label": "Constituent 1", "fill": "#0543bc" },
      { "id": "t97", "label": "Constituent 1", "fill": "#0543bc" },
      { "id": "t98", "label": "Constituent 1", "fill": "#0543bc" },
      { "id": "t99", "label": "Constituent 1", "fill": "#0543bc" },
      { "id": "t100", "label": "Constituent 1", "fill": "#0543bc" }
    ],
    [
      { "id": "t101", "label": "Constituent 1", "fill": "#F80018" },
      { "id": "t102", "label": "Constituent 1", "fill": "#F80018" },
      { "id": "t103", "label": "Constituent 1", "fill": "#F80018" },
      { "id": "t104", "label": "Constituent 1", "fill": "#F80018" },
      { "id": "t105", "label": "Constituent 1", "fill": "#F80018" },
      { "id": "t106", "label": "Constituent 1", "fill": "#F80018" },
      { "id": "t107", "label": "Constituent 1", "fill": "#F80018" },
      { "id": "t108", "label": "Constituent 1", "fill": "#F80018" },
      { "id": "t109", "label": "Constituent 1", "fill": "#F80018" },
      { "id": "t110", "label": "Constituent 1", "fill": "#F80018" },
      { "id": "t111", "label": "Constituent 1", "fill": "#F80018" },
      { "id": "t112", "label": "Constituent 1", "fill": "#F80018" },
      { "id": "t113", "label": "Constituent 1", "fill": "#F80018" },
      { "id": "t114", "label": "Constituent 1", "fill": "#F80018" },
      { "id": "t115", "label": "Constituent 1", "fill": "#F80018" },
      { "id": "t116", "label": "Constituent 1", "fill": "#F80018" },
      { "id": "t117", "label": "Constituent 1", "fill": "#F80018" },
      { "id": "t118", "label": "Constituent 1", "fill": "#F80018" },
      { "id": "t119", "label": "Constituent 1", "fill": "#F80018" },
      { "id": "t120", "label": "Constituent 1", "fill": "#F80018" },
      { "id": "t121", "label": "Constituent 1", "fill": "#F80018" },
      { "id": "t122", "label": "Constituent 1", "fill": "#F80018" },
      { "id": "t123", "label": "Constituent 1", "fill": "#F80018" },
      { "id": "t124", "label": "Constituent 1", "fill": "#F80018" },
      { "id": "t125", "label": "Constituent 1", "fill": "#F80018" },
      { "id": "t126", "label": "Constituent 1", "fill": "#F80018" },
      { "id": "t127", "label": "Constituent 1", "fill": "#F80018" },
      { "id": "t128", "label": "Constituent 1", "fill": "#F80018" },
      { "id": "t129", "label": "Constituent 1", "fill": "#F80018" },
      { "id": "t130", "label": "Constituent 1", "fill": "#F80018" },
      { "id": "t131", "label": "Constituent 1", "fill": "#F80018" },
      { "id": "t132", "label": "Constituent 1", "fill": "#F80018" },
      { "id": "t133", "label": "Constituent 1", "fill": "#F80018" },
      { "id": "t134", "label": "Constituent 1", "fill": "#F80018" },
      { "id": "t135", "label": "Constituent 1", "fill": "#F80018" },
      { "id": "t136", "label": "Constituent 1", "fill": "#F80018" },
      { "id": "t137", "label": "Constituent 1", "fill": "#F80018" },
      { "id": "t138", "label": "Constituent 1", "fill": "#F80018" },
      { "id": "t139", "label": "Constituent 1", "fill": "#F80018" },
      { "id": "t140", "label": "Constituent 1", "fill": "#F80018" },
      { "id": "t141", "label": "Constituent 1", "fill": "#F80018" },
      { "id": "t142", "label": "Constituent 1", "fill": "#F80018" },
      { "id": "t143", "label": "Constituent 1", "fill": "#F80018" },
      { "id": "t144", "label": "Constituent 1", "fill": "#F80018" },
      { "id": "t145", "label": "Constituent 1", "fill": "#F80018" },
      { "id": "t146", "label": "Constituent 1", "fill": "#F80018" },
      { "id": "t147", "label": "Constituent 1", "fill": "#F80018" },
      { "id": "t148", "label": "Constituent 1", "fill": "#F80018" },
      { "id": "t149", "label": "Constituent 1", "fill": "#F80018" },
      { "id": "t150", "label": "Constituent 1", "fill": "#F80018" },
      { "id": "t151", "label": "Constituent 1", "fill": "#F80018" },
      { "id": "t152", "label": "Constituent 1", "fill": "#F80018" },
      { "id": "t153", "label": "Constituent 1", "fill": "#F80018" },
      { "id": "t154", "label": "Constituent 1", "fill": "#F80018" },
      { "id": "t155", "label": "Constituent 1", "fill": "#F80018" },
      { "id": "t156", "label": "Constituent 1", "fill": "#F80018" },
      { "id": "t157", "label": "Constituent 1", "fill": "#F80018" },
      { "id": "t158", "label": "Constituent 1", "fill": "#F80018" },
      { "id": "t159", "label": "Constituent 1", "fill": "#F80018" },
      { "id": "t160", "label": "Constituent 1", "fill": "#F80018" },
      { "id": "t161", "label": "Constituent 1", "fill": "#F80018" },
      { "id": "t162", "label": "Constituent 1", "fill": "#F80018" },
      { "id": "t163", "label": "Constituent 1", "fill": "#F80018" },
      { "id": "t164", "label": "Constituent 1", "fill": "#F80018" },
      { "id": "t165", "label": "Constituent 1", "fill": "#F80018" },
      { "id": "t166", "label": "Constituent 1", "fill": "#F80018" },
      { "id": "t167", "label": "Constituent 1", "fill": "#F80018" },
      { "id": "t168", "label": "Constituent 1", "fill": "#F80018" },
      { "id": "t169", "label": "Constituent 1", "fill": "#F80018" },
      { "id": "t170", "label": "Constituent 1", "fill": "#F80018" },
      { "id": "t171", "label": "Constituent 1", "fill": "#F80018" },
      { "id": "t172", "label": "Constituent 1", "fill": "#F80018" },
      { "id": "t173", "label": "Constituent 1", "fill": "#F80018" },
      { "id": "t174", "label": "Constituent 1", "fill": "#F80018" },
      { "id": "t175", "label": "Constituent 1", "fill": "#F80018" },
      { "id": "t176", "label": "Constituent 1", "fill": "#F80018" },
      { "id": "t177", "label": "Constituent 1", "fill": "#F80018" },
      { "id": "t178", "label": "Constituent 1", "fill": "#F80018" },
      { "id": "t179", "label": "Constituent 1", "fill": "#F80018" },
      { "id": "t180", "label": "Constituent 1", "fill": "#F80018" },
      { "id": "t181", "label": "Constituent 1", "fill": "#F80018" },
      { "id": "t182", "label": "Constituent 1", "fill": "#F80018" },
      { "id": "t183", "label": "Constituent 1", "fill": "#F80018" },
      { "id": "t184", "label": "Constituent 1", "fill": "#F80018" },
      { "id": "t185", "label": "Constituent 1", "fill": "#F80018" },
      { "id": "t186", "label": "Constituent 1", "fill": "#F80018" },
      { "id": "t187", "label": "Constituent 1", "fill": "#F80018" },
      { "id": "t188", "label": "Constituent 1", "fill": "#F80018" },
      { "id": "t189", "label": "Constituent 1", "fill": "#F80018" },
      { "id": "t190", "label": "Constituent 1", "fill": "#F80018" },
      { "id": "t191", "label": "Constituent 1", "fill": "#F80018" },
      { "id": "t192", "label": "Constituent 1", "fill": "#F80018" },
      { "id": "t193", "label": "Constituent 1", "fill": "#F80018" },
      { "id": "t194", "label": "Constituent 1", "fill": "#F80018" },
      { "id": "t195", "label": "Constituent 1", "fill": "#F80018" },
      { "id": "t196", "label": "Constituent 1", "fill": "#F80018" },
      { "id": "t197", "label": "Constituent 1", "fill": "#F80018" },
      { "id": "t198", "label": "Constituent 1", "fill": "#F80018" },
      { "id": "t199", "label": "Constituent 1", "fill": "#F80018" },
      { "id": "t200", "label": "Constituent 1", "fill": "#F80018" },
      { "id": "t201", "label": "Constituent 1", "fill": "#F80018" },
      { "id": "t202", "label": "Constituent 1", "fill": "#F80018" },
      { "id": "t203", "label": "Constituent 1", "fill": "#F80018" },
      { "id": "t204", "label": "Constituent 1", "fill": "#F80018" },
      { "id": "t205", "label": "Constituent 1", "fill": "#F80018" },
      { "id": "t206", "label": "Constituent 1", "fill": "#F80018" },
      { "id": "t207", "label": "Constituent 1", "fill": "#F80018" },
      { "id": "t208", "label": "Constituent 1", "fill": "#F80018" },
      { "id": "t209", "label": "Constituent 1", "fill": "#F80018" },
      { "id": "t210", "label": "Constituent 1", "fill": "#F80018" },
      { "id": "t211", "label": "Constituent 1", "fill": "#F80018" },
      { "id": "t212", "label": "Constituent 1", "fill": "#F80018" },
      { "id": "t213", "label": "Constituent 1", "fill": "#F80018" },
      { "id": "t214", "label": "Constituent 1", "fill": "#F80018" },
      { "id": "t215", "label": "Constituent 1", "fill": "#F80018" },
      { "id": "t216", "label": "Constituent 1", "fill": "#F80018" },
      { "id": "t217", "label": "Constituent 1", "fill": "#F80018" },
      { "id": "t218", "label": "Constituent 1", "fill": "#F80018" },
      { "id": "t219", "label": "Constituent 1", "fill": "#F80018" },
      { "id": "t220", "label": "Constituent 1", "fill": "#F80018" },
      { "id": "t221", "label": "Constituent 1", "fill": "#F80018" },
      { "id": "t222", "label": "Constituent 1", "fill": "#F80018" },
      { "id": "t223", "label": "Constituent 1", "fill": "#F80018" },
      { "id": "t224", "label": "Constituent 1", "fill": "#F80018" },
      { "id": "t225", "label": "Constituent 1", "fill": "#F80018" },
      { "id": "t226", "label": "Constituent 1", "fill": "#F80018" },
      { "id": "t227", "label": "Constituent 1", "fill": "#F80018" },
      { "id": "t228", "label": "Constituent 1", "fill": "#F80018" },
      { "id": "t229", "label": "Constituent 1", "fill": "#F80018" },
      { "id": "t230", "label": "Constituent 1", "fill": "#F80018" },
      { "id": "t231", "label": "Constituent 1", "fill": "#F80018" }
    ]
  ],
  "links": [
    
    { "id": "L1", "from": "f5", "value": 3500, "to": "t147", "fill": "#F80018" },
    { "id": "L2", "from": "f8", "value": 1000, "to": "t39", "fill": "#0543bc" },
    { "id": "L3", "from": "f8", "value": 2500, "to": "t121", "fill": "#F80018" },
    { "id": "L4", "from": "f12", "value": 2500, "to": "t117", "fill": "#F80018" },
   
    { "id": "L9", "from": "f5", "value": 5000, "to": "t106", "fill": "#F80018" },
    { "id": "L10", "from": "f10", "value": 1000, "to": "t132", "fill": "#F80018" },
    { "id": "L11", "from": "f10", "value": 1500, "to": "t112", "fill": "#F80018" },
    { "id": "L12", "from": "f3", "value": 1000, "to": "t143", "fill": "#F80018" },
    { "id": "L13", "from": "f6", "value": 2500, "to": "t124", "fill": "#F80018" },
    { "id": "L14", "from": "f6", "value": 1000, "to": "t148", "fill": "#F80018" },
    { "id": "L15", "from": "f7", "value": 2500, "to": "t161", "fill": "#F80018" },
    { "id": "L16", "from": "f6", "value": 1000, "to": "t158", "fill": "#F80018" },
    
    { "id": "L18", "from": "f8", "value": 1000, "to": "t131", "fill": "#F80018" },
    
    
    { "id": "L21", "from": "f8", "value": 1000, "to": "t75", "fill": "#0543bc" },
    { "id": "L22", "from": "f10", "value": 1000, "to": "t118", "fill": "#F80018" },
    { "id": "L23", "from": "f6", "value": 1000, "to": "t200", "fill": "#F80018" },
    { "id": "L24", "from": "f3", "value": 3000, "to": "t27", "fill": "#0543bc" },
   
    
    { "id": "L29", "from": "f8", "value": 2500, "to": "t149", "fill": "#F80018" },
    { "id": "L30", "from": "f10", "value": 2000, "to": "t132", "fill": "#F80018" },
    { "id": "L31", "from": "f3", "value": 1000, "to": "t123", "fill": "#F80018" },
    { "id": "L32", "from": "f4", "value": 1000, "to": "t45", "fill": "#0543bc" },
    { "id": "L33", "from": "f3", "value": 1000, "to": "t134", "fill": "#F80018" },
    { "id": "L34", "from": "f12", "value": 5000, "to": "t114", "fill": "#F80018" },
    { "id": "L35", "from": "f12", "value": 2500, "to": "t32", "fill": "#0543bc" },
    { "id": "L36", "from": "f8", "value": 1500, "to": "t39", "fill": "#0543bc" },
    { "id": "L37", "from": "f3", "value": 1000, "to": "t3", "fill": "#0543bc" },
    { "id": "L38", "from": "f3", "value": 1000, "to": "t14", "fill": "#0543bc" },
    { "id": "L39", "from": "f3", "value": 1000, "to": "t219", "fill": "#F80018" },
    { "id": "L40", "from": "f3", "value": 1000, "to": "t170", "fill": "#F80018" },
    { "id": "L41", "from": "f3", "value": 1000, "to": "t189", "fill": "#F80018" },
    { "id": "L42", "from": "f3", "value": 1000, "to": "t19", "fill": "#0543bc" },
    { "id": "L43", "from": "f3", "value": 1000, "to": "t143", "fill": "#F80018" },
    
    { "id": "L45", "from": "f3", "value": 1000, "to": "t188", "fill": "#F80018" },
    { "id": "L46", "from": "f3", "value": 1000, "to": "t203", "fill": "#F80018" },
    { "id": "L47", "from": "f3", "value": 1000, "to": "t166", "fill": "#F80018" },
    { "id": "L48", "from": "f3", "value": 1000, "to": "t163", "fill": "#F80018" },
    { "id": "L49", "from": "f8", "value": 1000, "to": "t168", "fill": "#F80018" },
   
    { "id": "L51", "from": "f3", "value": 1000, "to": "t108", "fill": "#F80018" },
   
    { "id": "L54", "from": "f10", "value": 2000, "to": "t12", "fill": "#0543bc" },
    { "id": "L55", "from": "f10", "value": 1000, "to": "t155", "fill": "#F80018" },
    { "id": "L56", "from": "f3", "value": 1000, "to": "t184", "fill": "#F80018" },
    { "id": "L57", "from": "f3", "value": 1000, "to": "t55", "fill": "#0543bc" },
    { "id": "L58", "from": "f3", "value": 1000, "to": "t228", "fill": "#F80018" },
    { "id": "L59", "from": "f3", "value": 2000, "to": "t159", "fill": "#F80018" },
    { "id": "L60", "from": "f3", "value": 1000, "to": "t221", "fill": "#F80018" },
    
  
    { "id": "L63", "from": "f6", "value": 1500, "to": "t38", "fill": "#0543bc" },
    
    { "id": "L65", "from": "f12", "value": 10000, "to": "t102", "fill": "#F80018" },
   
    { "id": "L67", "from": "f3", "value": 1500, "to": "t122", "fill": "#F80018" },
    { "id": "L68", "from": "f3", "value": 2000, "to": "t112", "fill": "#F80018" },
    { "id": "L69", "from": "f3", "value": 1000, "to": "t37", "fill": "#0543bc" },
    { "id": "L70", "from": "f3", "value": 1000, "to": "t43", "fill": "#0543bc" },
    { "id": "L71", "from": "f3", "value": 2000, "to": "t22", "fill": "#0543bc" },
    { "id": "L72", "from": "f6", "value": 2000, "to": "t11", "fill": "#0543bc" },
    { "id": "L73", "from": "f8", "value": 1000, "to": "t164", "fill": "#F80018" },
    
    { "id": "L76", "from": "f3", "value": 1000, "to": "t153", "fill": "#F80018" },
    { "id": "L77", "from": "f3", "value": 2000, "to": "t133", "fill": "#F80018" },
    { "id": "L78", "from": "f3", "value": 1000, "to": "t72", "fill": "#0543bc" },
    { "id": "L79", "from": "f3", "value": 1000, "to": "t81", "fill": "#0543bc" },
    { "id": "L80", "from": "f8", "value": 2500, "to": "t121", "fill": "#F80018" },
    { "id": "L81", "from": "f8", "value": 1000, "to": "t208", "fill": "#F80018" },
    { "id": "L82", "from": "f3", "value": 2000, "to": "t33", "fill": "#0543bc" },
    { "id": "L83", "from": "f3", "value": 1000, "to": "t26", "fill": "#0543bc" },
    { "id": "L84", "from": "f8", "value": 1000, "to": "t206", "fill": "#F80018" },
    { "id": "L85", "from": "f7", "value": 1000, "to": "t150", "fill": "#F80018" },
    { "id": "L86", "from": "f7", "value": 1000, "to": "t12", "fill": "#0543bc" },
    { "id": "L87", "from": "f7", "value": 1000, "to": "t125", "fill": "#F80018" },
    { "id": "L88", "from": "f4", "value": 3000, "to": "t107", "fill": "#F80018" },
    { "id": "L89", "from": "f4", "value": 1000, "to": "t69", "fill": "#0543bc" },
    { "id": "L90", "from": "f5", "value": 1500, "to": "t36", "fill": "#0543bc" },
    { "id": "L91", "from": "f4", "value": 1000, "to": "t107", "fill": "#F80018" },
   
    { "id": "L94", "from": "f10", "value": 1000, "to": "t112", "fill": "#F80018" },
    { "id": "L95", "from": "f10", "value": 1000, "to": "t115", "fill": "#F80018" },
    { "id": "L96", "from": "f10", "value": 2000, "to": "t152", "fill": "#F80018" },
    { "id": "L97", "from": "f3", "value": 1000, "to": "t106", "fill": "#F80018" },
    { "id": "L98", "from": "f9", "value": 1000, "to": "t109", "fill": "#F80018" },
    { "id": "L99", "from": "f6", "value": 1000, "to": "t185", "fill": "#F80018" },
    { "id": "L100", "from": "f9", "value": 1000, "to": "t167", "fill": "#F80018" },
    { "id": "L101", "from": "f9", "value": 1500, "to": "t63", "fill": "#0543bc" },
   
    { "id": "L104", "from": "f9", "value": 1000, "to": "t183", "fill": "#F80018" },
 
    { "id": "L106", "from": "f3", "value": 1000, "to": "t14", "fill": "#0543bc" },
    { "id": "L107", "from": "f3", "value": 1000, "to": "t106", "fill": "#F80018" },
    { "id": "L108", "from": "f3", "value": 2000, "to": "t171", "fill": "#F80018" },
    { "id": "L109", "from": "f12", "value": 1000, "to": "t194", "fill": "#F80018" },
    { "id": "L110", "from": "f3", "value": 1000, "to": "t97", "fill": "#0543bc" },
    { "id": "L111", "from": "f3", "value": 1000, "to": "t40", "fill": "#0543bc" },
    { "id": "L112", "from": "f5", "value": 5000, "to": "t105", "fill": "#F80018" },
    { "id": "L113", "from": "f5", "value": 5000, "to": "t105", "fill": "#F80018" },
    { "id": "L114", "from": "f3", "value": 1500, "to": "t148", "fill": "#F80018" },
    { "id": "L115", "from": "f8", "value": 3000, "to": "t146", "fill": "#F80018" },
    { "id": "L116", "from": "f3", "value": 4000, "to": "t13", "fill": "#0543bc" },
    { "id": "L117", "from": "f10", "value": 2000, "to": "t14", "fill": "#0543bc" },
  
    { "id": "L120", "from": "f8", "value": 1000, "to": "t149", "fill": "#F80018" },
    { "id": "L121", "from": "f9", "value": 1000, "to": "t115", "fill": "#F80018" },
    
    { "id": "L123", "from": "f12", "value": 1000, "to": "t117", "fill": "#F80018" },
    { "id": "L124", "from": "f10", "value": 1000, "to": "t118", "fill": "#F80018" },
    { "id": "L125", "from": "f10", "value": 1000, "to": "t112", "fill": "#F80018" },
    { "id": "L126", "from": "f3", "value": 1000, "to": "t22", "fill": "#0543bc" },
    { "id": "L127", "from": "f3", "value": 1000, "to": "t19", "fill": "#0543bc" },
    { "id": "L128", "from": "f3", "value": 1000, "to": "t141", "fill": "#F80018" },
    { "id": "L129", "from": "f3", "value": 1000, "to": "t52", "fill": "#0543bc" },
    { "id": "L130", "from": "f3", "value": 2000, "to": "t153", "fill": "#F80018" },
    { "id": "L131", "from": "f9", "value": 1000, "to": "t181", "fill": "#F80018" },
    { "id": "L132", "from": "f3", "value": 1000, "to": "t222", "fill": "#F80018" },
    { "id": "L133", "from": "f6", "value": 2500, "to": "t24", "fill": "#0543bc" },
    
    { "id": "L135", "from": "f6", "value": 1000, "to": "t103", "fill": "#F80018" },
    { "id": "L136", "from": "f5", "value": 5000, "to": "t30", "fill": "#0543bc" },
   
    { "id": "L138", "from": "f3", "value": 2000, "to": "t141", "fill": "#F80018" },
    { "id": "L139", "from": "f6", "value": 1000, "to": "t151", "fill": "#F80018" },
   
    { "id": "L141", "from": "f3", "value": 1000, "to": "t143", "fill": "#F80018" },
    { "id": "L142", "from": "f3", "value": 1000, "to": "t156", "fill": "#F80018" },
    { "id": "L143", "from": "f3", "value": 1000, "to": "t47", "fill": "#0543bc" },
    { "id": "L144", "from": "f3", "value": 5000, "to": "t116", "fill": "#F80018" },
    { "id": "L145", "from": "f3", "value": 2000, "to": "t191", "fill": "#F80018" },
    { "id": "L146", "from": "f3", "value": 1000, "to": "t123", "fill": "#F80018" },
    { "id": "L147", "from": "f3", "value": 4000, "to": "t116", "fill": "#F80018" },
    { "id": "L148", "from": "f9", "value": 1000, "to": "t213", "fill": "#F80018" },
    { "id": "L149", "from": "f9", "value": 1000, "to": "t122", "fill": "#F80018" },
    { "id": "L150", "from": "f9", "value": 1000, "to": "t225", "fill": "#F80018" },
    { "id": "L151", "from": "f9", "value": 1000, "to": "t114", "fill": "#F80018" },
    { "id": "L152", "from": "f9", "value": 1000, "to": "t150", "fill": "#F80018" },
    { "id": "L153", "from": "f8", "value": 1000, "to": "t110", "fill": "#F80018" },
    { "id": "L154", "from": "f10", "value": 2500, "to": "t21", "fill": "#0543bc" },
    { "id": "L155", "from": "f9", "value": 1000, "to": "t137", "fill": "#F80018" },
    
    { "id": "L157", "from": "f10", "value": 1000, "to": "t35", "fill": "#0543bc" },
    { "id": "L158", "from": "f3", "value": 2000, "to": "t190", "fill": "#F80018" },
    { "id": "L159", "from": "f6", "value": 1000, "to": "t106", "fill": "#F80018" },
   
    { "id": "L161", "from": "f3", "value": 1000, "to": "t133", "fill": "#F80018" },
    { "id": "L162", "from": "f6", "value": 1000, "to": "t123", "fill": "#F80018" },
    { "id": "L163", "from": "f3", "value": 2000, "to": "t134", "fill": "#F80018" },
    
    { "id": "L165", "from": "f12", "value": 1000, "to": "t138", "fill": "#F80018" },
    { "id": "L166", "from": "f3", "value": 1000, "to": "t20", "fill": "#0543bc" },
    { "id": "L167", "from": "f3", "value": 3000, "to": "t103", "fill": "#F80018" },
    { "id": "L168", "from": "f3", "value": 1000, "to": "t143", "fill": "#F80018" },
    
    
    { "id": "L171", "from": "f3", "value": 2000, "to": "t46", "fill": "#0543bc" },
    { "id": "L172", "from": "f3", "value": 1000, "to": "t101", "fill": "#F80018" },
    { "id": "L173", "from": "f8", "value": 2500, "to": "t131", "fill": "#F80018" },
    { "id": "L174", "from": "f8", "value": 2500, "to": "t179", "fill": "#F80018" },
    { "id": "L175", "from": "f10", "value": 2000, "to": "t152", "fill": "#F80018" },
    { "id": "L176", "from": "f10", "value": 1000, "to": "t12", "fill": "#0543bc" },
    { "id": "L177", "from": "f10", "value": 1000, "to": "t157", "fill": "#F80018" },
    { "id": "L178", "from": "f3", "value": 1000, "to": "t169", "fill": "#F80018" },
    { "id": "L179", "from": "f3", "value": 1000, "to": "t163", "fill": "#F80018" },
    { "id": "L180", "from": "f6", "value": 1000, "to": "t107", "fill": "#F80018" },
    { "id": "L181", "from": "f9", "value": 1000, "to": "t162", "fill": "#F80018" },
    { "id": "L182", "from": "f8", "value": 2500, "to": "t103", "fill": "#F80018" },
    
    
    { "id": "L185", "from": "f7", "value": 1000, "to": "t161", "fill": "#F80018" },
    
    
    { "id": "L188", "from": "f10", "value": 1000, "to": "t103", "fill": "#F80018" },
    { "id": "L189", "from": "f3", "value": 1000, "to": "t223", "fill": "#F80018" },
    { "id": "L190", "from": "f3", "value": 1000, "to": "t103", "fill": "#F80018" },
    { "id": "L191", "from": "f4", "value": 1000, "to": "t45", "fill": "#0543bc" },
    { "id": "L192", "from": "f4", "value": 1000, "to": "t137", "fill": "#F80018" },
    { "id": "L193", "from": "f3", "value": 2000, "to": "t103", "fill": "#F80018" },
    { "id": "L194", "from": "f3", "value": 1000, "to": "t60", "fill": "#0543bc" },
    { "id": "L195", "from": "f4", "value": 1000, "to": "t166", "fill": "#F80018" },
    { "id": "L196", "from": "f4", "value": 1000, "to": "t77", "fill": "#0543bc" },
    { "id": "L197", "from": "f4", "value": 1000, "to": "t229", "fill": "#F80018" },
    { "id": "L198", "from": "f4", "value": 1000, "to": "t117", "fill": "#F80018" },
    { "id": "L199", "from": "f4", "value": 5000, "to": "t117", "fill": "#F80018" },
    { "id": "L206", "from": "f3", "value": 1000, "to": "t230", "fill": "#F80018" },
    { "id": "L212", "from": "f9", "value": 1000, "to": "t74", "fill": "#0543bc" },
    
    { "id": "L214", "from": "f9", "value": 1000, "to": "t60", "fill": "#0543bc" },
   
    { "id": "L217", "from": "f4", "value": 1000, "to": "t198", "fill": "#F80018" },
    { "id": "L218", "from": "f4", "value": 1000, "to": "t50", "fill": "#0543bc" },
    { "id": "L219", "from": "f4", "value": 2500, "to": "t118", "fill": "#F80018" },
    { "id": "L220", "from": "f4", "value": 1000, "to": "t122", "fill": "#F80018" },
    { "id": "L221", "from": "f6", "value": 2500, "to": "t129", "fill": "#F80018" },
    { "id": "L222", "from": "f3", "value": 2000, "to": "t33", "fill": "#0543bc" },
   
    { "id": "L224", "from": "f5", "value": 5000, "to": "t104", "fill": "#F80018" },
    { "id": "L225", "from": "f5", "value": 5000, "to": "t15", "fill": "#0543bc" },
    { "id": "L226", "from": "f4", "value": 2000, "to": "t170", "fill": "#F80018" },
    { "id": "L227", "from": "f5", "value": 5000, "to": "t7", "fill": "#0543bc" },
    
    
    { "id": "L231", "from": "f10", "value": 1500, "to": "t21", "fill": "#0543bc" },
    { "id": "L232", "from": "f10", "value": 1000, "to": "t14", "fill": "#0543bc" },
    { "id": "L233", "from": "f8", "value": 2500, "to": "t145", "fill": "#F80018" },
    
    { "id": "L239", "from": "f8", "value": 2000, "to": "t146", "fill": "#F80018" },
    { "id": "L240", "from": "f12", "value": 5000, "to": "t102", "fill": "#F80018" },
    { "id": "L241", "from": "f12", "value": 5000, "to": "t102", "fill": "#F80018" },
   
  
   
    { "id": "L245", "from": "f4", "value": 2000, "to": "t41", "fill": "#0543bc" },
  
    { "id": "L247", "from": "f8", "value": 2500, "to": "t102", "fill": "#F80018" },
    { "id": "L248", "from": "f5", "value": 1000, "to": "t79", "fill": "#0543bc" },
   
    { "id": "L250", "from": "f10", "value": 1000, "to": "t112", "fill": "#F80018" },
    { "id": "L251", "from": "f4", "value": 1000, "to": "t183", "fill": "#F80018" },
    { "id": "L252", "from": "f4", "value": 1000, "to": "t23", "fill": "#0543bc" },
    { "id": "L253", "from": "f8", "value": 2500, "to": "t121", "fill": "#F80018" },
    { "id": "L254", "from": "f4", "value": 1000, "to": "t89", "fill": "#0543bc" },
    { "id": "L255", "from": "f4", "value": 1000, "to": "t123", "fill": "#F80018" },
    { "id": "L256", "from": "f6", "value": 2500, "to": "t11", "fill": "#0543bc" },
    { "id": "L257", "from": "f9", "value": 1000, "to": "t92", "fill": "#0543bc" },
    { "id": "L258", "from": "f6", "value": 1000, "to": "t106", "fill": "#F80018" },
    { "id": "L259", "from": "f6", "value": 4000, "to": "t106", "fill": "#F80018" },
    { "id": "L260", "from": "f8", "value": 1000, "to": "t109", "fill": "#F80018" },
  
    { "id": "L262", "from": "f4", "value": 1000, "to": "t165", "fill": "#F80018" },
    { "id": "L263", "from": "f4", "value": 1000, "to": "t43", "fill": "#0543bc" },
    { "id": "L264", "from": "f4", "value": 2000, "to": "t58", "fill": "#0543bc" },
    { "id": "L265", "from": "f6", "value": 2500, "to": "t124", "fill": "#F80018" },
    { "id": "L266", "from": "f6", "value": 2500, "to": "t124", "fill": "#F80018" },
    
   
    { "id": "L270", "from": "f7", "value": 1000, "to": "t98", "fill": "#0543bc" },
    { "id": "L271", "from": "f7", "value": 2500, "to": "t150", "fill": "#F80018" },
    { "id": "L272", "from": "f5", "value": 3000, "to": "t6", "fill": "#0543bc" },
   
    { "id": "L274", "from": "f7", "value": 1000, "to": "t54", "fill": "#0543bc" },
    { "id": "L275", "from": "f8", "value": 1000, "to": "t114", "fill": "#F80018" },
    { "id": "L276", "from": "f4", "value": 1000, "to": "t171", "fill": "#F80018" },
    { "id": "L277", "from": "f4", "value": 1000, "to": "t26", "fill": "#0543bc" },
    { "id": "L278", "from": "f4", "value": 1000, "to": "t137", "fill": "#F80018" },
    { "id": "L279", "from": "f4", "value": 1000, "to": "t82", "fill": "#0543bc" },
    { "id": "L280", "from": "f9", "value": 1000, "to": "t201", "fill": "#F80018" },
    { "id": "L281", "from": "f4", "value": 1000, "to": "t40", "fill": "#0543bc" },
    { "id": "L282", "from": "f4", "value": 1000, "to": "t122", "fill": "#F80018" },
    { "id": "L283", "from": "f4", "value": 4000, "to": "t103", "fill": "#F80018" },
    { "id": "L284", "from": "f6", "value": 1000, "to": "t168", "fill": "#F80018" },
    { "id": "L285", "from": "f4", "value": 2000, "to": "t49", "fill": "#0543bc" },
    { "id": "L286", "from": "f5", "value": 5000, "to": "t19", "fill": "#0543bc" },
    { "id": "L287", "from": "f8", "value": 1000, "to": "t103", "fill": "#F80018" },
    { "id": "L288", "from": "f9", "value": 1000, "to": "t137", "fill": "#F80018" },
    { "id": "L289", "from": "f9", "value": 1000, "to": "t140", "fill": "#F80018" },
   
    { "id": "L291", "from": "f9", "value": 1000, "to": "t186", "fill": "#F80018" },
    { "id": "L292", "from": "f9", "value": 1000, "to": "t167", "fill": "#F80018" },
    { "id": "L293", "from": "f5", "value": 5000, "to": "t7", "fill": "#0543bc" },
    { "id": "L294", "from": "f3", "value": 2000, "to": "t134", "fill": "#F80018" },
    { "id": "L295", "from": "f6", "value": 1000, "to": "t148", "fill": "#F80018" },
    { "id": "L296", "from": "f6", "value": 1000, "to": "t158", "fill": "#F80018" },
    { "id": "L297", "from": "f3", "value": 1000, "to": "t134", "fill": "#F80018" },
    { "id": "L298", "from": "f5", "value": 5000, "to": "t15", "fill": "#0543bc" },
    { "id": "L299", "from": "f10", "value": 1000, "to": "t132", "fill": "#F80018" },
   
    { "id": "L301", "from": "f7", "value": 2000, "to": "t59", "fill": "#0543bc" },
    { "id": "L302", "from": "f6", "value": 2500, "to": "t176", "fill": "#F80018" },
    { "id": "L303", "from": "f7", "value": 1000, "to": "t99", "fill": "#0543bc" },
    { "id": "L305", "from": "f4", "value": 4000, "to": "t129", "fill": "#F80018" },
    { "id": "L306", "from": "f4", "value": 1000, "to": "t27", "fill": "#0543bc" },
    { "id": "L307", "from": "f4", "value": 1000, "to": "t27", "fill": "#0543bc" },
    { "id": "L308", "from": "f10", "value": 3500, "to": "t12", "fill": "#0543bc" },
    { "id": "L309", "from": "f6", "value": 1000, "to": "t168", "fill": "#F80018" },
   
    { "id": "L312", "from": "f8", "value": 1000, "to": "t39", "fill": "#0543bc" },
   
    { "id": "L315", "from": "f7", "value": 1000, "to": "t216", "fill": "#F80018" },
    { "id": "L316", "from": "f8", "value": 1000, "to": "t149", "fill": "#F80018" },
    { "id": "L317", "from": "f3", "value": 1000, "to": "t50", "fill": "#0543bc" },
    { "id": "L318", "from": "f3", "value": 2000, "to": "t106", "fill": "#F80018" },
    { "id": "L319", "from": "f3", "value": 1000, "to": "t141", "fill": "#F80018" },
    
  
    { "id": "L322", "from": "f8", "value": 1000, "to": "t205", "fill": "#F80018" },
   
    { "id": "L324", "from": "f3", "value": 1000, "to": "t122", "fill": "#F80018" },
    { "id": "L325", "from": "f3", "value": 1000, "to": "t184", "fill": "#F80018" },
    { "id": "L326", "from": "f8", "value": 1000, "to": "t111", "fill": "#F80018" },
    { "id": "L327", "from": "f9", "value": 2000, "to": "t42", "fill": "#0543bc" },
   
    { "id": "L329", "from": "f3", "value": 1000, "to": "t45", "fill": "#0543bc" },
    { "id": "L330", "from": "f3", "value": 1000, "to": "t189", "fill": "#F80018" },
    { "id": "L331", "from": "f3", "value": 1000, "to": "t163", "fill": "#F80018" },
    { "id": "L332", "from": "f3", "value": 3000, "to": "t156", "fill": "#F80018" },
    
    
    { "id": "L335", "from": "f9", "value": 1000, "to": "t133", "fill": "#F80018" },
    { "id": "L336", "from": "f7", "value": 2000, "to": "t140", "fill": "#F80018" },
    { "id": "L337", "from": "f3", "value": 1000, "to": "t55", "fill": "#0543bc" },
    { "id": "L338", "from": "f3", "value": 1000, "to": "t186", "fill": "#F80018" },
    { "id": "L339", "from": "f3", "value": 1000, "to": "t125", "fill": "#F80018" },
    { "id": "L340", "from": "f8", "value": 2500, "to": "t131", "fill": "#F80018" },
    { "id": "L341", "from": "f3", "value": 1000, "to": "t19", "fill": "#0543bc" },
    { "id": "L342", "from": "f8", "value": 1000, "to": "t121", "fill": "#F80018" },
    { "id": "L343", "from": "f3", "value": 1000, "to": "t211", "fill": "#F80018" },
    { "id": "L344", "from": "f3", "value": 2000, "to": "t37", "fill": "#0543bc" },
    { "id": "L345", "from": "f3", "value": 1000, "to": "t52", "fill": "#0543bc" },
    { "id": "L346", "from": "f3", "value": 1000, "to": "t47", "fill": "#0543bc" },
    { "id": "L347", "from": "f3", "value": 1000, "to": "t43", "fill": "#0543bc" },
    
    { "id": "L349", "from": "f10", "value": 2000, "to": "t155", "fill": "#F80018" },
    { "id": "L350", "from": "f10", "value": 1000, "to": "t112", "fill": "#F80018" },
    { "id": "L351", "from": "f10", "value": 1000, "to": "t14", "fill": "#0543bc" },
    { "id": "L352", "from": "f10", "value": 1000, "to": "t103", "fill": "#F80018" },
    { "id": "L353", "from": "f9", "value": 1000, "to": "t114", "fill": "#F80018" },
    { "id": "L354", "from": "f9", "value": 1000, "to": "t115", "fill": "#F80018" },
    { "id": "L355", "from": "f7", "value": 2500, "to": "t172", "fill": "#F80018" },
    { "id": "L356", "from": "f7", "value": 2000, "to": "t192", "fill": "#F80018" },
    { "id": "L357", "from": "f3", "value": 2000, "to": "t14", "fill": "#0543bc" },
    { "id": "L358", "from": "f3", "value": 1000, "to": "t11", "fill": "#0543bc" },
    { "id": "L359", "from": "f3", "value": 2000, "to": "t107", "fill": "#F80018" },
    { "id": "L360", "from": "f3", "value": 1000, "to": "t188", "fill": "#F80018" },
    { "id": "L361", "from": "f3", "value": 1000, "to": "t148", "fill": "#F80018" },
    { "id": "L362", "from": "f6", "value": 1000, "to": "t151", "fill": "#F80018" },
    { "id": "L363", "from": "f3", "value": 1000, "to": "t157", "fill": "#F80018" },
   
    { "id": "L365", "from": "f6", "value": 1000, "to": "t25", "fill": "#0543bc" },
    { "id": "L366", "from": "f3", "value": 1000, "to": "t41", "fill": "#0543bc" },
    { "id": "L367", "from": "f10", "value": 1000, "to": "t14", "fill": "#0543bc" },
    { "id": "L368", "from": "f10", "value": 2000, "to": "t103", "fill": "#F80018" },
    { "id": "L369", "from": "f10", "value": 1000, "to": "t85", "fill": "#0543bc" },
    { "id": "L370", "from": "f7", "value": 1000, "to": "t67", "fill": "#F80018" },
    { "id": "L371", "from": "f7", "value": 1000, "to": "t106", "fill": "#F80018" },
    { "id": "L372", "from": "f7", "value": 1000, "to": "t220", "fill": "#F80018" },
    
    { "id": "L374", "from": "f7", "value": 1000, "to": "t125", "fill": "#F80018" },
    { "id": "L375", "from": "f7", "value": 2000, "to": "t140", "fill": "#F80018" },
    
    { "id": "L377", "from": "f6", "value": 1000, "to": "t87", "fill": "#0543bc" },
    
    { "id": "L379", "from": "f6", "value": 1000, "to": "t123", "fill": "#F80018" },
    { "id": "L380", "from": "f10", "value": 2000, "to": "t118", "fill": "#F80018" },
    
    { "id": "L382", "from": "f9", "value": 1000, "to": "t84", "fill": "#0543bc" },
    { "id": "L383", "from": "f9", "value": 2500, "to": "t10", "fill": "#0543bc" },
    { "id": "L384", "from": "f9", "value": 1500, "to": "t62", "fill": "#0543bc" },
    { "id": "L385", "from": "f9", "value": 1000, "to": "t91", "fill": "#0543bc" },
    { "id": "L386", "from": "f9", "value": 1000, "to": "t93", "fill": "#0543bc" },
    { "id": "L387", "from": "f9", "value": 1000, "to": "t100", "fill": "#0543bc" },
    { "id": "L388", "from": "f4", "value": 3000, "to": "t22", "fill": "#0543bc" },
    { "id": "L389", "from": "f4", "value": 2000, "to": "t115", "fill": "#F80018" },
    { "id": "L390", "from": "f1", "value": 691, "to": "t2", "fill": "#0543bc" },
    { "id": "L391", "from": "f1", "value": 3459, "to": "t1", "fill": "#0543bc" },
    { "id": "L392", "from": "f7", "value": 1000, "to": "t78", "fill": "#0543bc" },
    { "id": "L393", "from": "f7", "value": 1000, "to": "t204", "fill": "#F80018" },
    { "id": "L394", "from": "f7", "value": 1000, "to": "t68", "fill": "#0543bc" },
    { "id": "L395", "from": "f7", "value": 1000, "to": "t196", "fill": "#F80018" },
    { "id": "L396", "from": "f7", "value": 1000, "to": "t112", "fill": "#F80018" },
    { "id": "L397", "from": "f7", "value": 1500, "to": "t12", "fill": "#0543bc" },
    { "id": "L398", "from": "f7", "value": 1000, "to": "t215", "fill": "#F80018" },
    { "id": "L399", "from": "f7", "value": 1000, "to": "t22", "fill": "#0543bc" },
    { "id": "L400", "from": "f7", "value": 1000, "to": "t96", "fill": "#0543bc" },
    { "id": "L401", "from": "f7", "value": 1000, "to": "t14", "fill": "#0543bc" },
    { "id": "L402", "from": "f7", "value": 2500, "to": "t174", "fill": "#F80018" },
    { "id": "L403", "from": "f7", "value": 1000, "to": "t209", "fill": "#F80018" },
    { "id": "L404", "from": "f7", "value": 1000, "to": "t90", "fill": "#0543bc" },
    { "id": "L405", "from": "f7", "value": 1000, "to": "t21", "fill": "#0543bc" },
    { "id": "L406", "from": "f7", "value": 5000, "to": "t28", "fill": "#0543bc" },
    { "id": "L407", "from": "f7", "value": 1000, "to": "t158", "fill": "#F80018" },
    { "id": "L408", "from": "f7", "value": 1000, "to": "t185", "fill": "#F80018" },
    { "id": "L409", "from": "f7", "value": 2500, "to": "t13", "fill": "#0543bc" },
    { "id": "L410", "from": "f7", "value": 1000, "to": "t218", "fill": "#F80018" },
    { "id": "L411", "from": "f9", "value": 1000, "to": "t80", "fill": "#0543bc" },
    { "id": "L412", "from": "f7", "value": 1000, "to": "t38", "fill": "#0543bc" },
    { "id": "L413", "from": "f9", "value": 1000, "to": "t212", "fill": "#F80018" },
    { "id": "L414", "from": "f4", "value": 2000, "to": "t21", "fill": "#0543bc" },
    { "id": "L415", "from": "f4", "value": 1000, "to": "t195", "fill": "#F80018" },
    { "id": "L416", "from": "f4", "value": 1000, "to": "t181", "fill": "#F80018" },
    { "id": "L417", "from": "f4", "value": 1000, "to": "t166", "fill": "#F80018" },
    { "id": "L418", "from": "f4", "value": 1000, "to": "t193", "fill": "#F80018" },
    { "id": "L419", "from": "f4", "value": 1000, "to": "t153", "fill": "#F80018" },
    { "id": "L420", "from": "f4", "value": 1000, "to": "t143", "fill": "#F80018" },
    { "id": "L421", "from": "f4", "value": 1000, "to": "t106", "fill": "#F80018" },
    { "id": "L422", "from": "f4", "value": 1000, "to": "t125", "fill": "#F80018" },
    { "id": "L423", "from": "f4", "value": 1000, "to": "t207", "fill": "#F80018" },
    { "id": "L424", "from": "f4", "value": 1000, "to": "t159", "fill": "#F80018" },
    { "id": "L425", "from": "f4", "value": 1000, "to": "t165", "fill": "#F80018" },
    { "id": "L426", "from": "f4", "value": 1000, "to": "t151", "fill": "#F80018" },
    { "id": "L427", "from": "f4", "value": 1000, "to": "t40", "fill": "#0543bc" },
  
    { "id": "L430", "from": "f4", "value": 1000, "to": "t20", "fill": "#0543bc" },
    { "id": "L431", "from": "f4", "value": 2000, "to": "t112", "fill": "#F80018" },
    { "id": "L433", "from": "f2", "value": 541, "to": "t119", "fill": "#F80018" },
    { "id": "L434", "from": "f4", "value": 2000, "to": "t12", "fill": "#0543bc" },
    { "id": "L435", "from": "f4", "value": 1000, "to": "t9", "fill": "#0543bc" },
    { "id": "L436", "from": "f2", "value": 541, "to": "t10", "fill": "#0543bc" },
    { "id": "L437", "from": "f2", "value": 541, "to": "t10", "fill": "#0543bc" },
    { "id": "L439", "from": "f2", "value": 541, "to": "t119", "fill": "#F80018" },
    { "id": "L440", "from": "f6", "value": 2000, "to": "t24", "fill": "#0543bc" },
    { "id": "L441", "from": "f6", "value": 1000, "to": "t24", "fill": "#0543bc" },
    { "id": "L442", "from": "f2", "value": 541, "to": "t10", "fill": "#0543bc" },
    { "id": "L443", "from": "f2", "value": 541, "to": "t119", "fill": "#F80018" },
    { "id": "L444", "from": "f6", "value": 2500, "to": "t103", "fill": "#F80018" },
    { "id": "L445", "from": "f6", "value": 4000, "to": "t11", "fill": "#0543bc" },
    { "id": "L446", "from": "f6", "value": 1000, "to": "t151", "fill": "#F80018" },
    { "id": "L447", "from": "f2", "value": 541, "to": "t10", "fill": "#0543bc" },
    { "id": "L448", "from": "f2", "value": 541, "to": "t119", "fill": "#F80018" },
    { "id": "L449", "from": "f6", "value": 1000, "to": "t11", "fill": "#0543bc" },
    { "id": "L450", "from": "f2", "value": 541, "to": "t119", "fill": "#F80018" },
    { "id": "L451", "from": "f2", "value": 541, "to": "t10", "fill": "#0543bc" },
    { "id": "L452", "from": "f9", "value": 1000, "to": "t210", "fill": "#F80018" },
    { "id": "L453", "from": "f9", "value": 1000, "to": "t224", "fill": "#F80018" },
    { "id": "L454", "from": "f9", "value": 1000, "to": "t116", "fill": "#F80018" },
    { "id": "L455", "from": "f9", "value": 1000, "to": "t231", "fill": "#F80018" },
    { "id": "L456", "from": "f12", "value": 4000, "to": "t138", "fill": "#F80018" },
  
    { "id": "L459", "from": "f2", "value": 812, "to": "t10", "fill": "#0543bc" },
  
    { "id": "L461", "from": "f9", "value": 1000, "to": "t86", "fill": "#0543bc" },
  
    { "id": "L463", "from": "f2", "value": 812, "to": "t119", "fill": "#F80018" },
  
    { "id": "L465", "from": "f4", "value": 1000, "to": "t226", "fill": "#F80018" },
    { "id": "L466", "from": "f4", "value": 2000, "to": "t44", "fill": "#0543bc" },
    { "id": "L467", "from": "f4", "value": 1000, "to": "t141", "fill": "#F80018" },
    { "id": "L468", "from": "f8", "value": 2500, "to": "t132", "fill": "#F80018" },
    { "id": "L469", "from": "f2", "value": 812, "to": "t119", "fill": "#F80018" },
    { "id": "L470", "from": "f4", "value": 1000, "to": "t158", "fill": "#F80018" },
    { "id": "L471", "from": "f4", "value": 3000, "to": "t123", "fill": "#F80018" },
    { "id": "L472", "from": "f4", "value": 3000, "to": "t105", "fill": "#F80018" },
    { "id": "L473", "from": "f4", "value": 1000, "to": "t122", "fill": "#F80018" },
    { "id": "L474", "from": "f4", "value": 1000, "to": "t26", "fill": "#0543bc" },
    { "id": "L475", "from": "f4", "value": 1000, "to": "t38", "fill": "#0543bc" },
    { "id": "L476", "from": "f4", "value": 1000, "to": "t133", "fill": "#F80018" },
    { "id": "L477", "from": "f2", "value": 812, "to": "t10", "fill": "#0543bc" },
    { "id": "L478", "from": "f4", "value": 1000, "to": "t214", "fill": "#F80018" },
    { "id": "L479", "from": "f4", "value": 1000, "to": "t155", "fill": "#F80018" },
    { "id": "L480", "from": "f4", "value": 1000, "to": "t125", "fill": "#F80018" },
    { "id": "L481", "from": "f4", "value": 1000, "to": "t202", "fill": "#F80018" },
    { "id": "L482", "from": "f4", "value": 1000, "to": "t159", "fill": "#F80018" },
    { "id": "L483", "from": "f4", "value": 1000, "to": "t137", "fill": "#F80018" },
    
    { "id": "L487", "from": "f2", "value": 812, "to": "t119", "fill": "#F80018" },
    { "id": "L488", "from": "f6", "value": 2000, "to": "t187", "fill": "#F80018" },
    
    { "id": "L490", "from": "f2", "value": 812, "to": "t10", "fill": "#0543bc" },
    { "id": "L491", "from": "f4", "value": 1000, "to": "t133", "fill": "#F80018" },
    { "id": "L492", "from": "f2", "value": 812, "to": "t119", "fill": "#F80018" },
    { "id": "L493", "from": "f7", "value": 2500, "to": "t178", "fill": "#F80018" },
    { "id": "L494", "from": "f2", "value": 812, "to": "t10", "fill": "#0543bc" },
    { "id": "L495", "from": "f2", "value": 812, "to": "t119", "fill": "#F80018" },
    { "id": "L496", "from": "f2", "value": 812, "to": "t10", "fill": "#0543bc" },
    { "id": "L497", "from": "f8", "value": 2500, "to": "t145", "fill": "#F80018" },
    
    { "id": "L499", "from": "f5", "value": 5000, "to": "t128", "fill": "#F80018" },
  
    { "id": "L502", "from": "f9", "value": 1000, "to": "t44", "fill": "#0543bc" },
    { "id": "L503", "from": "f9", "value": 1000, "to": "t83", "fill": "#0543bc" },
  
    { "id": "L505", "from": "f2", "value": 541, "to": "t119", "fill": "#F80018" },
    { "id": "L506", "from": "f2", "value": 541, "to": "t10", "fill": "#0543bc" },
    { "id": "L507", "from": "f2", "value": 541, "to": "t119", "fill": "#F80018" },
    { "id": "L508", "from": "f1", "value": 136387, "to": "t1", "fill": "#0543bc" },
    { "id": "L509", "from": "f2", "value": 541, "to": "t10", "fill": "#0543bc" },
    { "id": "L510", "from": "f1", "value": 68193, "to": "t2", "fill": "#0543bc" },
    { "id": "L511", "from": "f4", "value": 2000, "to": "t13", "fill": "#0543bc" },
    { "id": "L512", "from": "f4", "value": 2000, "to": "t23", "fill": "#0543bc" },
    { "id": "L513", "from": "f2", "value": 541, "to": "t10", "fill": "#0543bc" },
    { "id": "L514", "from": "f2", "value": 541, "to": "t119", "fill": "#F80018" },
    { "id": "L515", "from": "f2", "value": 541, "to": "t10", "fill": "#0543bc" },
    { "id": "L516", "from": "f2", "value": 541, "to": "t119", "fill": "#F80018" },
    { "id": "L517", "from": "f2", "value": 541, "to": "t119", "fill": "#F80018" },
    { "id": "L518", "from": "f2", "value": 541, "to": "t10", "fill": "#0543bc" },
    { "id": "L519", "from": "f7", "value": 1000, "to": "t76", "fill": "#0543bc" },
    { "id": "L520", "from": "f7", "value": 1000, "to": "t19", "fill": "#0543bc" },
    { "id": "L521", "from": "f2", "value": 1148, "to": "t101", "fill": "#F80018" },
    { "id": "L522", "from": "f2", "value": 1148, "to": "t5", "fill": "#0543bc" },
    { "id": "L523", "from": "f2", "value": 1223, "to": "t5", "fill": "#0543bc" },
    { "id": "L524", "from": "f2", "value": 1223, "to": "t101", "fill": "#F80018" },
    
    { "id": "L526", "from": "f2", "value": 1223, "to": "t5", "fill": "#0543bc" },
    { "id": "L527", "from": "f2", "value": 1223, "to": "t101", "fill": "#F80018" },
    
    { "id": "L529", "from": "f2", "value": 1223, "to": "t5", "fill": "#0543bc" },
    { "id": "L530", "from": "f2", "value": 1223, "to": "t101", "fill": "#F80018" },
    { "id": "L531", "from": "f2", "value": 1223, "to": "t5", "fill": "#0543bc" },
    { "id": "L532", "from": "f2", "value": 1223, "to": "t101", "fill": "#F80018" },
    { "id": "L533", "from": "f2", "value": 1223, "to": "t101", "fill": "#F80018" },
    { "id": "L534", "from": "f2", "value": 1223, "to": "t5", "fill": "#0543bc" },
    { "id": "L535", "from": "f2", "value": 1303, "to": "t101", "fill": "#F80018" },
    { "id": "L536", "from": "f2", "value": 1303, "to": "t5", "fill": "#0543bc" },
    { "id": "L537", "from": "f2", "value": 1648, "to": "t5", "fill": "#0543bc" },
    { "id": "L538", "from": "f2", "value": 1648, "to": "t101", "fill": "#F80018" },
    { "id": "L539", "from": "f2", "value": 1869, "to": "t101", "fill": "#F80018" },
    { "id": "L540", "from": "f2", "value": 1869, "to": "t5", "fill": "#0543bc" },
    { "id": "L541", "from": "f2", "value": 2362, "to": "t4", "fill": "#0543bc" },
   
    { "id": "L543", "from": "f2", "value": 2362, "to": "t4", "fill": "#0543bc" },
    { "id": "L544", "from": "f2", "value": 1869, "to": "t101", "fill": "#F80018" },
   
    { "id": "L547", "from": "f4", "value": 2000, "to": "t53", "fill": "#0543bc" },
    { "id": "L548", "from": "f2", "value": 1869, "to": "t5", "fill": "#0543bc" },
    { "id": "L549", "from": "f2", "value": 2362, "to": "t4", "fill": "#0543bc" },
    { "id": "L550", "from": "f2", "value": 1818, "to": "t4", "fill": "#0543bc" },
    { "id": "L551", "from": "f2", "value": 1818, "to": "t4", "fill": "#0543bc" },
    { "id": "L552", "from": "f2", "value": 1966, "to": "t101", "fill": "#F80018" },
    { "id": "L553", "from": "f2", "value": 1966, "to": "t5", "fill": "#0543bc" },
    { "id": "L554", "from": "f2", "value": 632, "to": "t7", "fill": "#0543bc" },
    { "id": "L555", "from": "f2", "value": 689, "to": "t7", "fill": "#0543bc" },
    { "id": "L556", "from": "f2", "value": 1076, "to": "t7", "fill": "#0543bc" },
    { "id": "L557", "from": "f2", "value": 1818, "to": "t4", "fill": "#0543bc" },
    { "id": "L558", "from": "f2", "value": 2081, "to": "t4", "fill": "#0543bc" },
    { "id": "L559", "from": "f2", "value": 2081, "to": "t4", "fill": "#0543bc" },
    { "id": "L560", "from": "f2", "value": 538, "to": "t104", "fill": "#F80018" },
    { "id": "L561", "from": "f2", "value": 1522, "to": "t61", "fill": "#0543bc" },
    { "id": "L562", "from": "f2", "value": 2081, "to": "t4", "fill": "#0543bc" },
    { "id": "L563", "from": "f2", "value": 538, "to": "t6", "fill": "#0543bc" },
    { "id": "L564", "from": "f2", "value": 1522, "to": "t122", "fill": "#F80018" },
    { "id": "L565", "from": "f2", "value": 2290, "to": "t4", "fill": "#0543bc" },
    { "id": "L566", "from": "f2", "value": 538, "to": "t6", "fill": "#0543bc" },
   
    { "id": "L568", "from": "f2", "value": 538, "to": "t104", "fill": "#F80018" },
    { "id": "L569", "from": "f2", "value": 538, "to": "t104", "fill": "#F80018" },
    { "id": "L570", "from": "f2", "value": 2290, "to": "t4", "fill": "#0543bc" },
    { "id": "L571", "from": "f6", "value": 4000, "to": "t25", "fill": "#0543bc" },
    { "id": "L572", "from": "f2", "value": 538, "to": "t6", "fill": "#0543bc" },
    { "id": "L573", "from": "f2", "value": 1615, "to": "t6", "fill": "#0543bc" },
    { "id": "L574", "from": "f2", "value": 580, "to": "t6", "fill": "#0543bc" },
    { "id": "L575", "from": "f2", "value": 580, "to": "t104", "fill": "#F80018" },
    { "id": "L576", "from": "f2", "value": 1025, "to": "t104", "fill": "#F80018" },
    { "id": "L577", "from": "f2", "value": 1615, "to": "t104", "fill": "#F80018" },
    { "id": "L578", "from": "f2", "value": 949, "to": "t104", "fill": "#F80018" },
    { "id": "L579", "from": "f2", "value": 2430, "to": "t101", "fill": "#F80018" },
    { "id": "L580", "from": "f2", "value": 1025, "to": "t6", "fill": "#0543bc" },
    { "id": "L581", "from": "f2", "value": 2430, "to": "t5", "fill": "#0543bc" },
    { "id": "L582", "from": "f2", "value": 2027, "to": "t4", "fill": "#0543bc" },
    { "id": "L583", "from": "f2", "value": 949, "to": "t6", "fill": "#0543bc" },
    { "id": "L584", "from": "f2", "value": 538, "to": "t104", "fill": "#F80018" },
    { "id": "L585", "from": "f2", "value": 2350, "to": "t5", "fill": "#0543bc" },
    { "id": "L586", "from": "f2", "value": 2350, "to": "t101", "fill": "#F80018" },
    { "id": "L587", "from": "f2", "value": 2027, "to": "t4", "fill": "#0543bc" },
    { "id": "L588", "from": "f2", "value": 538, "to": "t6", "fill": "#0543bc" },
    { "id": "L589", "from": "f2", "value": 2569, "to": "t4", "fill": "#0543bc" },
    { "id": "L590", "from": "f2", "value": 2420, "to": "t5", "fill": "#0543bc" },
    { "id": "L591", "from": "f2", "value": 2420, "to": "t101", "fill": "#F80018" },
    { "id": "L592", "from": "f2", "value": 540, "to": "t6", "fill": "#0543bc" },
    { "id": "L593", "from": "f2", "value": 2420, "to": "t101", "fill": "#F80018" },
    { "id": "L594", "from": "f2", "value": 538, "to": "t104", "fill": "#F80018" },
    { "id": "L595", "from": "f11", "value": 20000, "to": "t3", "fill": "#0543bc" },
    { "id": "L596", "from": "f2", "value": 1712, "to": "t4", "fill": "#0543bc" },
    { "id": "L597", "from": "f2", "value": 2420, "to": "t5", "fill": "#0543bc" },
    { "id": "L598", "from": "f2", "value": 1712, "to": "t8", "fill": "#0543bc" },
    { "id": "L599", "from": "f2", "value": 538, "to": "t6", "fill": "#0543bc" },
    { "id": "L600", "from": "f2", "value": 2284, "to": "t101", "fill": "#F80018" },
    { "id": "L601", "from": "f4", "value": 1000, "to": "t9", "fill": "#0543bc" },
    { "id": "L602", "from": "f2", "value": 538, "to": "t6", "fill": "#0543bc" },
    { "id": "L603", "from": "f2", "value": 538, "to": "t104", "fill": "#F80018" },
    { "id": "L604", "from": "f2", "value": 1712, "to": "t4", "fill": "#0543bc" },
    { "id": "L605", "from": "f2", "value": 2284, "to": "t5", "fill": "#0543bc" },
    { "id": "L606", "from": "f2", "value": 1712, "to": "t8", "fill": "#0543bc" },
    { "id": "L607", "from": "f2", "value": 2352, "to": "t5", "fill": "#0543bc" },
    { "id": "L608", "from": "f2", "value": 538, "to": "t104", "fill": "#F80018" },
    { "id": "L609", "from": "f2", "value": 1712, "to": "t4", "fill": "#0543bc" },
    { "id": "L610", "from": "f2", "value": 2352, "to": "t101", "fill": "#F80018" },
    { "id": "L611", "from": "f2", "value": 1712, "to": "t8", "fill": "#0543bc" },
    { "id": "L612", "from": "f2", "value": 538, "to": "t6", "fill": "#0543bc" },
    { "id": "L613", "from": "f2", "value": 538, "to": "t104", "fill": "#F80018" },
    { "id": "L614", "from": "f2", "value": 1712, "to": "t4", "fill": "#0543bc" },
    { "id": "L615", "from": "f2", "value": 2352, "to": "t101", "fill": "#F80018" },
    { "id": "L616", "from": "f2", "value": 538, "to": "t6", "fill": "#0543bc" },
    { "id": "L617", "from": "f2", "value": 1712, "to": "t8", "fill": "#0543bc" },
    { "id": "L618", "from": "f2", "value": 2352, "to": "t5", "fill": "#0543bc" },
    { "id": "L619", "from": "f2", "value": 1712, "to": "t8", "fill": "#0543bc" },
    { "id": "L620", "from": "f2", "value": 2352, "to": "t5", "fill": "#0543bc" },
    { "id": "L621", "from": "f2", "value": 1712, "to": "t4", "fill": "#0543bc" },
    { "id": "L622", "from": "f2", "value": 538, "to": "t104", "fill": "#F80018" },
    { "id": "L623", "from": "f2", "value": 2352, "to": "t101", "fill": "#F80018" },
    { "id": "L624", "from": "f2", "value": 538, "to": "t6", "fill": "#0543bc" },
    { "id": "L625", "from": "f2", "value": 1712, "to": "t4", "fill": "#0543bc" },
    { "id": "L626", "from": "f2", "value": 538, "to": "t6", "fill": "#0543bc" },
    { "id": "L627", "from": "f2", "value": 2352, "to": "t101", "fill": "#F80018" },
    { "id": "L628", "from": "f2", "value": 1712, "to": "t8", "fill": "#0543bc" },
    { "id": "L629", "from": "f2", "value": 2352, "to": "t5", "fill": "#0543bc" },
    { "id": "L630", "from": "f2", "value": 538, "to": "t104", "fill": "#F80018" },
    
    { "id": "L632", "from": "f2", "value": 1006, "to": "t4", "fill": "#0543bc" },
    { "id": "L633", "from": "f2", "value": 2469, "to": "t101", "fill": "#F80018" },
    { "id": "L634", "from": "f2", "value": 538, "to": "t6", "fill": "#0543bc" },
    { "id": "L635", "from": "f2", "value": 2469, "to": "t5", "fill": "#0543bc" },
  
    { "id": "L637", "from": "f2", "value": 1006, "to": "t8", "fill": "#0543bc" },
    { "id": "L638", "from": "f2", "value": 538, "to": "t104", "fill": "#F80018" },
    { "id": "L639", "from": "f2", "value": 538, "to": "t104", "fill": "#F80018" },
    { "id": "L640", "from": "f11", "value": 23000, "to": "t3", "fill": "#0543bc" },
    { "id": "L641", "from": "f2", "value": 2469, "to": "t5", "fill": "#0543bc" },
    { "id": "L642", "from": "f2", "value": 2469, "to": "t101", "fill": "#F80018" },
  
    { "id": "L644", "from": "f2", "value": 1006, "to": "t8", "fill": "#0543bc" },
    { "id": "L645", "from": "f2", "value": 538, "to": "t6", "fill": "#0543bc" },
    { "id": "L646", "from": "f2", "value": 1006, "to": "t4", "fill": "#0543bc" },
    { "id": "L647", "from": "f8", "value": 5000, "to": "t108", "fill": "#F80018" },
   
    { "id": "L649", "from": "f4", "value": 1000, "to": "t11", "fill": "#0543bc" },
    { "id": "L650", "from": "f4", "value": 2000, "to": "t56", "fill": "#0543bc"}
  ]
}